{
  "sample_rate": 48000,
  "bpm": 110,
  "duration_s": 16,
  "init": [
    {"_comment":"The Spotymod (VCV host) init patch, rendered for verification. Mirrors the module's default knob values 1:1 (host/vcv/src/Spotymod.cpp defaultFor + configControls): only module-exposed setters, center left neutral. Part A / left = a sustained minor-9 drone; part B / right = a low bass melody. Global Dorian holds every min9 tone (A C E G B). Verified content: A ~330-590 Hz, ~3 voices stacked on the min9 tones; B ~120-220 Hz, plucky stepped line."},
    {"action":"set_scale","value":"dorian"},

    {"_comment":"PART A / left = min9 drone: slow stepped modulator + very long decay so 3-4 voices ring together across the Dorian degrees."},
    {"action":"set_engine","part":0,"value":"synth"},
    {"action":"set_sync_mode","part":0,"value":"sync"},
    {"action":"set_rate","part":0,"value":0.10},
    {"action":"set_step","part":0,"flag":true,"ivalue":6},
    {"action":"set_shape","part":0,"value":0.40},
    {"action":"set_range","part":0,"value":0.45},
    {"action":"set_smooth","part":0,"value":0.50},
    {"action":"set_probability","part":0,"value":0.90},
    {"action":"set_depth","part":0,"value":0.50},
    {"action":"set_tune","part":0,"value":0.50},
    {"action":"set_voice_attack","part":0,"value":0.20},
    {"action":"set_voice_decay","part":0,"value":0.90},
    {"action":"set_voice_resonance","part":0,"value":0.20},
    {"action":"set_voice_sub","part":0,"value":0.30},
    {"action":"set_voice_detune","part":0,"value":0.20},
    {"action":"set_comp","part":0,"value":0.30},

    {"_comment":"PART B / right = bass melody: tune fully down (~A2 floor), stepped 8-note sequence, plucky short decay, sub weight."},
    {"action":"set_engine","part":1,"value":"synth"},
    {"action":"set_sync_mode","part":1,"value":"sync"},
    {"action":"set_rate","part":1,"value":0.20},
    {"action":"set_step","part":1,"flag":true,"ivalue":8},
    {"action":"set_shape","part":1,"value":0.70},
    {"action":"set_range","part":1,"value":0.30},
    {"action":"set_smooth","part":1,"value":0.20},
    {"action":"set_probability","part":1,"value":0.90},
    {"action":"set_depth","part":1,"value":0.60},
    {"action":"set_tune","part":1,"value":0.00},
    {"action":"set_voice_attack","part":1,"value":0.05},
    {"action":"set_voice_decay","part":1,"value":0.16},
    {"action":"set_voice_resonance","part":1,"value":0.25},
    {"action":"set_voice_sub","part":1,"value":0.50},
    {"action":"set_voice_detune","part":1,"value":0.10},
    {"action":"set_comp","part":1,"value":0.20},

    {"_comment":"Long, roomy tail under the drone (matches the module's reverb defaults)."},
    {"action":"set_reverb_size","value":0.70},
    {"action":"set_reverb_tone","value":0.55},
    {"action":"set_reverb_decay","value":0.80},
    {"action":"set_reverb_depth","value":0.25},
    {"action":"set_master_drive","value":0.50}
  ],
  "events": []
}
